odoo9_addon_stock_picking_back2draft-9.0.1.0.0.99.dev2-py3.8-nspkg.pth
odoo_addons/stock_picking_back2draft/README.rst
odoo_addons/stock_picking_back2draft/__init__.py
odoo_addons/stock_picking_back2draft/__openerp__.py
odoo_addons/stock_picking_back2draft/i18n/de.po
odoo_addons/stock_picking_back2draft/i18n/es.po
odoo_addons/stock_picking_back2draft/i18n/fi.po
odoo_addons/stock_picking_back2draft/i18n/fr.po
odoo_addons/stock_picking_back2draft/i18n/it.po
odoo_addons/stock_picking_back2draft/i18n/sl.po
odoo_addons/stock_picking_back2draft/i18n/stock_picking_back2draft.pot
odoo_addons/stock_picking_back2draft/images/picking.png
odoo_addons/stock_picking_back2draft/models/__init__.py
odoo_addons/stock_picking_back2draft/models/stock.py
odoo_addons/stock_picking_back2draft/static/description/icon.png
odoo_addons/stock_picking_back2draft/tests/__init__.py
odoo_addons/stock_picking_back2draft/tests/test_picking.py
odoo_addons/stock_picking_back2draft/views/picking_view.xml
odoo9_addon_stock_picking_back2draft-9.0.1.0.0.99.dev2.dist-info/METADATA
odoo9_addon_stock_picking_back2draft-9.0.1.0.0.99.dev2.dist-info/WHEEL
odoo9_addon_stock_picking_back2draft-9.0.1.0.0.99.dev2.dist-info/namespace_packages.txt
odoo9_addon_stock_picking_back2draft-9.0.1.0.0.99.dev2.dist-info/top_level.txt
odoo9_addon_stock_picking_back2draft-9.0.1.0.0.99.dev2.dist-info/RECORD
